setup.py
My_chat_server.egg-info/PKG-INFO
My_chat_server.egg-info/SOURCES.txt
My_chat_server.egg-info/dependency_links.txt
My_chat_server.egg-info/requires.txt
My_chat_server.egg-info/top_level.txt
server/__init__.py
server/decorators.py
server/descriptors.py
server/metaclasses.py
server/server_core.py
server/server_crypt.py
server/server_db.py
server/start_server.py
server/jim/__init__.py
server/jim/codes.py
server/jim/constants.py
server/jim/functions.py
server/jim/classes/__init__.py
server/jim/classes/package.py
server/jim/classes/request_body.py
server/logs/__init__.py
server/logs/server_log_config.py
server/ui/__init__.py
server/ui/server_config_ui.py
server/ui/server_ui.py
server/ui/server_ui_logic.py