Metadata-Version: 1.0
Name: My-chat-server
Version: 0.0.2
Summary: My_chat_server
Home-page: UNKNOWN
Author: Sergey Sergeev
Author-email: ss2576@mail.ru
License: UNKNOWN
Platform: UNKNOWN
